sonarr_mcp_server/__init__.py
sonarr_mcp_server/server.py
sonarr_mcp-0.1.0.dist-info/METADATA
sonarr_mcp-0.1.0.dist-info/WHEEL
sonarr_mcp-0.1.0.dist-info/entry_points.txt
sonarr_mcp-0.1.0.dist-info/RECORD
