Metadata-Version: 2.4
Name: sonarr-mcp
Version: 0.1.0
Summary: MCP server for Sonarr tv-show management
Requires-Python: >=3.13
Requires-Dist: httpx>=0.27.0
Requires-Dist: mcp>=1.0.0
Requires-Dist: pydantic>=2.0.0
